canonicaljson/__init__.py
canonicaljson/py.typed
canonicaljson-1.6.5.dist-info/LICENSE
canonicaljson-1.6.5.dist-info/METADATA
canonicaljson-1.6.5.dist-info/WHEEL
canonicaljson-1.6.5.dist-info/top_level.txt
canonicaljson-1.6.5.dist-info/zip-safe
canonicaljson-1.6.5.dist-info/RECORD
