Metadata-Version: 2.1
Name: canonicaljson
Version: 1.6.5
Summary: Canonical JSON
Home-page: https://github.com/matrix-org/python-canonicaljson
Author: Matrix.org Team and Contributors
Author-email: packages@matrix.org
License: Apache License, Version 2.0
Keywords: json
Classifier: Development Status :: 5 - Production/Stable
Classifier: Intended Audience :: Developers
Classifier: License :: OSI Approved :: Apache Software License
Classifier: Programming Language :: Python :: 2
Classifier: Programming Language :: Python :: 3
Requires-Python: >=3.7
License-File: LICENSE
Requires-Dist: simplejson (>=3.14.0)
Requires-Dist: typing-extensions (>=4.0.0) ; python_version < "3.8"
Provides-Extra: frozendict
Requires-Dist: frozendict (>=1.0) ; extra == 'frozendict'
